macaroni/__init__.py
macaroni/consts.py
macaroni/decorators.py
macaroni/macaroni.py
macaroni/types.py
macaroni-0.0.3.dist-info/LICENSE.md
macaroni-0.0.3.dist-info/METADATA
macaroni-0.0.3.dist-info/WHEEL
macaroni-0.0.3.dist-info/top_level.txt
macaroni-0.0.3.dist-info/RECORD
