Metadata-Version: 2.1
Name: macaroni
Version: 0.0.3
Summary: A lib to help you avoid spaghetti code
Home-page: https://github.com/rudineirk/py-macaroni
Author: Rudinei Goi Roecker
Author-email: rudinei.roecker@gmail.com
License: MIT
Keywords: clean cleancode logic functional
Platform: UNKNOWN
Classifier: Development Status :: 3 - Alpha
Classifier: Intended Audience :: Developers
Classifier: Topic :: Software Development :: Libraries :: Application Frameworks
Classifier: License :: OSI Approved :: MIT License
Classifier: Programming Language :: Python :: 3
Classifier: Programming Language :: Python :: 3.6
